feathercarver/__init__.py
feathercarver/__main__.py
feathercarver/argument_parser.py
feathercarver/directory_processor.py
feathercarver/file_processor.py
feathercarver/link_fixer.py
feathercarver/logger.py
feathercarver-0.1.26.dist-info/METADATA
feathercarver-0.1.26.dist-info/WHEEL
feathercarver-0.1.26.dist-info/entry_points.txt
feathercarver-0.1.26.dist-info/RECORD
