Metadata-Version: 2.3
Name: feathercarver
Version: 0.1.26
Summary: A Python tool to fix broken Markdown links in files
Author-email: Taylor Monacelli <taylormonacelli@gmail.com>
Requires-Python: >=3.8
